setup.cfg
setup.py
saifmohamed/__init__.py
saifmohamed/min.py
saifmohamed/show.py
saifmohamed.egg-info/PKG-INFO
saifmohamed.egg-info/SOURCES.txt
saifmohamed.egg-info/dependency_links.txt
saifmohamed.egg-info/not-zip-safe
saifmohamed.egg-info/top_level.txt