Metadata-Version: 2.1
Name: saifmohamed
Version: 0.0.1
Summary: Only for testing
Author-email: saifmohamed23@gamil.com
